next_dict/__init__.py
next_dict/next_config_manager.py
next_dict/next_dict_obj.py
next_dict-0.2.1.dist-info/LICENSE
next_dict-0.2.1.dist-info/METADATA
next_dict-0.2.1.dist-info/WHEEL
next_dict-0.2.1.dist-info/top_level.txt
next_dict-0.2.1.dist-info/RECORD
