Metadata-Version: 2.1
Name: next_dict
Version: 0.2.1
Summary: json dict and config file manager
Home-page: https://github.com/Rymfader/next_dict
Author: Albert
License: MIT
Classifier: License :: OSI Approved :: MIT License
Classifier: Programming Language :: Python
Classifier: Programming Language :: Python :: 3
Classifier: Programming Language :: Python :: 3.6
Classifier: Programming Language :: Python :: Implementation :: CPython
Classifier: Programming Language :: Python :: Implementation :: PyPy
Requires-Python: >=3.6.0
License-File: LICENSE
